LICENSE.txt
setup.py
blickfeld_qb2/__init__.py
blickfeld_qb2.egg-info/PKG-INFO
blickfeld_qb2.egg-info/SOURCES.txt
blickfeld_qb2.egg-info/dependency_links.txt
blickfeld_qb2.egg-info/requires.txt
blickfeld_qb2.egg-info/top_level.txt
blickfeld_qb2/base/__init__.py
blickfeld_qb2/base/config/__init__.py
blickfeld_qb2/base/data/__init__.py
blickfeld_qb2/base/geometry/__init__.py
blickfeld_qb2/base/grpc/__init__.py
blickfeld_qb2/base/grpc/aio_channel.py
blickfeld_qb2/base/grpc/aio_server_interceptor.py
blickfeld_qb2/base/grpc/base_error.py
blickfeld_qb2/base/grpc/channel.py
blickfeld_qb2/base/grpc/constants.py
blickfeld_qb2/base/grpc/device_ca_cert.py
blickfeld_qb2/beam_deflection_control/__init__.py
blickfeld_qb2/beam_deflection_control/config/__init__.py
blickfeld_qb2/beam_deflection_control/data/__init__.py
blickfeld_qb2/beam_deflection_control/services/__init__.py
blickfeld_qb2/betterproto/__init__.py
blickfeld_qb2/betterproto/_types.py
blickfeld_qb2/betterproto/casing.py
blickfeld_qb2/betterproto/py.typed
blickfeld_qb2/betterproto/compile/__init__.py
blickfeld_qb2/betterproto/compile/importing.py
blickfeld_qb2/betterproto/compile/naming.py
blickfeld_qb2/betterproto/grpc/__init__.py
blickfeld_qb2/betterproto/grpc/grpclib_client.py
blickfeld_qb2/betterproto/grpc/grpclib_server.py
blickfeld_qb2/betterproto/grpc/util/__init__.py
blickfeld_qb2/betterproto/grpc/util/async_channel.py
blickfeld_qb2/betterproto/lib/__init__.py
blickfeld_qb2/betterproto/lib/google/__init__.py
blickfeld_qb2/betterproto/lib/google/protobuf/__init__.py
blickfeld_qb2/betterproto/lib/google/protobuf/compiler/__init__.py
blickfeld_qb2/betterproto/plugin/__init__.py
blickfeld_qb2/betterproto/plugin/__main__.py
blickfeld_qb2/betterproto/plugin/compiler.py
blickfeld_qb2/betterproto/plugin/main.py
blickfeld_qb2/betterproto/plugin/models.py
blickfeld_qb2/betterproto/plugin/parser.py
blickfeld_qb2/compute_module/__init__.py
blickfeld_qb2/compute_module/data/__init__.py
blickfeld_qb2/compute_module/services/__init__.py
blickfeld_qb2/config/__init__.py
blickfeld_qb2/config/data/__init__.py
blickfeld_qb2/config/services/__init__.py
blickfeld_qb2/core_processing/__init__.py
