Metadata-Version: 2.1
Name: blickfeld_qb2
Version: 2.14.5
Summary: Python package to communicate securely with Qb2 LiDAR devices of the Blickfeld GmbH
Home-page: https://github.com/Blickfeld/blickfeld-qb2
Author: Blickfeld GmbH
Author-email: opensource@blickfeld.com
License-File: LICENSE.txt
Requires-Dist: numpy
Requires-Dist: grpclib>=0.4.1
Requires-Dist: python-dateutil>=2.8
Requires-Dist: dataclasses>=0.7; python_version < "3.7"
